setup.py
src/pyxhook/__init__.py
src/pyxhook/pyxhook.py
src/pyxhook.egg-info/PKG-INFO
src/pyxhook.egg-info/SOURCES.txt
src/pyxhook.egg-info/dependency_links.txt
src/pyxhook.egg-info/requires.txt
src/pyxhook.egg-info/top_level.txt
test/test_runner.py