Metadata-Version: 1.0
Name: pyxhook
Version: 1.0.0
Summary: Packaged version of pyxhook
Home-page: https://github.com/patamechanix/pyxhook/
Author: patamechanix
Author-email: UNKNOWN
License: GNU version 2
Platform: UNKNOWN
